strategy_bridge/__init__.py
strategy_bridge/bus/__init__.py
strategy_bridge/bus/data_bus.py
strategy_bridge/bus/data_reader.py
strategy_bridge/bus/data_writer.py
strategy_bridge/bus/record.py
strategy_bridge/common/__init__.py
strategy_bridge/common/config.py
strategy_bridge/larcmacs/__init__.py
strategy_bridge/larcmacs/receiver.py
strategy_bridge/main.py
strategy_bridge/matlab/__init__.py
strategy_bridge/matlab/engine.py
strategy_bridge/model/__init__.py
strategy_bridge/model/referee.py
strategy_bridge/model/vision.py
strategy_bridge/pb/__init__.py
strategy_bridge/pb/grsim_commands_pb2.py
strategy_bridge/pb/grsim_packet_pb2.py
strategy_bridge/pb/grsim_replacement_pb2.py
strategy_bridge/pb/messages_robocup_ssl_detection_pb2.py
strategy_bridge/pb/messages_robocup_ssl_geometry_legacy_pb2.py
strategy_bridge/pb/messages_robocup_ssl_geometry_pb2.py
strategy_bridge/pb/messages_robocup_ssl_refbox_log_pb2.py
strategy_bridge/pb/messages_robocup_ssl_wrapper_legacy_pb2.py
strategy_bridge/pb/messages_robocup_ssl_wrapper_pb2.py
strategy_bridge/pb/ssl_simulation_robot_control_pb2.py
strategy_bridge/processors/__init__.py
strategy_bridge/processors/base_processor.py
strategy_bridge/processors/box_feedback_collector.py
strategy_bridge/processors/matlab_controller.py
strategy_bridge/processors/python_controller_template.py
strategy_bridge/processors/referee_commands_collector.py
strategy_bridge/processors/robot_commands_sender.py
strategy_bridge/processors/vision_combiner.py
strategy_bridge/processors/vision_detections_collector.py
strategy_bridge/runner.py
strategy_bridge/utils/__init__.py
strategy_bridge/utils/debugger.py
strategy_bridge-0.4.2.dist-info/METADATA
strategy_bridge-0.4.2.dist-info/WHEEL
strategy_bridge-0.4.2.dist-info/RECORD
