Metadata-Version: 2.1
Name: strategy-bridge
Version: 0.4.2
Summary: 
Author: Mikhail Lipkovich
Author-email: lipkovich.mikhail@gmail.com
Requires-Python: >=3.9,<3.13
Classifier: Programming Language :: Python :: 3
Classifier: Programming Language :: Python :: 3.9
Classifier: Programming Language :: Python :: 3.10
Classifier: Programming Language :: Python :: 3.11
Requires-Dist: attrs (>=23.1.0,<24.0.0)
Requires-Dist: matlab (>=0.1,<0.2)
Requires-Dist: numpy (>=1.26.0,<2.0.0)
Requires-Dist: protobuf (==3.19.1)
Requires-Dist: pyzmq (>=25.1.1,<26.0.0)
Requires-Dist: websocket-client (>=1.6.4,<2.0.0)
